crickly/__init__.py
crickly/core/__init__.py
crickly/core/admin.py
crickly/core/models.py
crickly/core/tests.py
crickly/core/migrations/0001_initial.py
crickly/core/migrations/0002_auto_20190110_1822.py
crickly/core/migrations/0003_auto_20190127_2041.py
crickly/core/migrations/0004_auto_20190410_1724.py
crickly/core/migrations/__init__.py
crickly/core/urls/__init__.py
crickly/core/urls/api.py
crickly/core/urls/matches.py
crickly/core/urls/stats.py
crickly/core/views/__init__.py
crickly/core/views/exceptions.py
crickly/core/views/stats.py
crickly/core/views/view_decorators.py
crickly/core/views/api/__init__.py
crickly/core/views/api/fixtures.py
crickly/core/views/api/generic.py
crickly/core/views/api/results.py
crickly/core/views/api/stats_batting.py
crickly/core/views/api/stats_bowling.py
crickly/core/views/api/stats_fielding.py
crickly/core/views/api/stats_generic.py
crickly/core/views/api/view_decorators.py
crickly/core/views/generic/__init__.py
crickly/core/views/generic/argument_view.py
crickly/core/views/match/__init__.py
crickly/core/views/match/fixtures.py
crickly/core/views/match/generic.py
crickly/core/views/match/index.py
crickly/core/views/match/match.py
crickly/core/views/match/results.py
crickly/core/views/statsV2/__init__.py
crickly-0.1.0.dist-info/LICENSE
crickly-0.1.0.dist-info/METADATA
crickly-0.1.0.dist-info/WHEEL
crickly-0.1.0.dist-info/top_level.txt
crickly-0.1.0.dist-info/RECORD
