Metadata-Version: 2.1
Name: crickly
Version: 0.1.0
Summary: A Django app to store and manage cricket matches.
Home-page: https://rly.rocks/s/crickly
Author: Riley Evans
Author-email: crickly@rileyevans.co.uk
License: MIT License
Platform: UNKNOWN
Classifier: Environment :: Web Environment
Classifier: Framework :: Django
Classifier: Intended Audience :: Developers
Classifier: Operating System :: OS Independent
Classifier: Programming Language :: Python
Classifier: Programming Language :: Python :: 3.5
Classifier: Programming Language :: Python :: 3.6
Classifier: Topic :: Internet :: WWW/HTTP
Classifier: Topic :: Internet :: WWW/HTTP :: Dynamic Content
Requires-Dist: Django (<2.0.0,>=1.11.0)
